LICENSE
docs/assets/logo.png
nhound/__init__.py
nhound/cohort.py
nhound/console.py
nhound/dehumanize.py
nhound/email.py
nhound/inotion.py
nhound/user.py
nhound/utils.py
nhound-0.1.1.dist-info/LICENSE
nhound-0.1.1.dist-info/METADATA
nhound-0.1.1.dist-info/WHEEL
nhound-0.1.1.dist-info/entry_points.txt
nhound-0.1.1.dist-info/RECORD
