Metadata-Version: 2.1
Name: nhound
Version: 0.1.1
Summary: Notion hound, as in nagging you to keep content up to date.
Home-page: https://github.com/worldr/nhound
License: MIT
Keywords: worldr
Author: Dr Yann Golanski
Author-email: ygg@worldr.com
Requires-Python: >=3.9,<3.12
Classifier: License :: OSI Approved :: MIT License
Classifier: Programming Language :: Python :: 3
Classifier: Programming Language :: Python :: 3.9
Classifier: Programming Language :: Python :: 3.10
Classifier: Programming Language :: Python :: 3.11
Requires-Dist: click (>=8.1.3,<9.0.0)
Requires-Dist: click-help-colors (>=0.9.1,<0.10.0)
Requires-Dist: notion-client (>=2.0.0,<3.0.0)
Requires-Dist: orjson (>=3.8.12,<4.0.0)
Requires-Dist: pendulum (>=2.1.2,<3.0.0)
Requires-Dist: python-dotenv (>=1.0.0,<2.0.0)
Requires-Dist: redmail (>=0.6.0,<0.7.0)
Requires-Dist: requests (>=2.30.0,<3.0.0)
Requires-Dist: rich (>=13.3.5,<14.0.0)
Requires-Dist: structlog (>=23.1.0,<24.0.0)
Requires-Dist: types-requests (>=2.30.0.0,<3.0.0.0)
Project-URL: Repository, https://github.com/worldr/nhound
